{
  "fighters": [
    {
      "id": 1,
      "name": "Mario",
      "franchise": "Super Mario Bros.",
      "bio": "Mario is an all-around fighter who uses his wide variety of techniques to respond to any situation. In Super Smash Bros. Ultimate, he shows up in his Wedding tux and his Builder outfit, and Cappy even makes an appearance!",
      "videoID": "INk1W8OujQI"
    },
    {
      "id": 2,
      "name": "Donkey Kong",
      "franchise": "Donkey Kong",
      "bio": "His charged punch is one of the strongest attacks in the game! In Super Smash Bros. Ultimate, his Final Smash has been updated from Konga Beat to a flurry of punches!",
      "videoID": "K7IsUGeFXP0"
    },
    {
      "id": 3,
      "name": "Link",
      "franchise": "The Legend of Zelda",
      "bio": "Link has been redesigned to match his appearance in The Legend of Zelda: Breath of the Wild. He can now pick up arrows he's fired, and his bombs have been upgraded to remote bombs, so you can set them off when the timing is just right!",
      "videoID": "kfeUdBi67G4"
    },
    {
      "id": 4,
      "name": "Samus",
      "franchise": "Metroid",
      "bio": "With her Charge Shot, Missile, and Bomb, Samus has three different projectiles to keep her opponents in check from a distance. When fully charged up, her Charge Shot is quite powerful. For her Final Smash, she launches a wide laser beam that can be moved up and down!",
      "videoID": "I9tcvSeemVo"
    },
    {
      "id": 4.1,
      "name": "Dark Samus",
      "franchise": "Metroid",
      "bio": "Dark Samus joins the battle as Samus's echo fighter.With floatier movement, she's a little different from Samus--and she doesn't roll when dodging or jumping. If you look closely, you can see that her bombs and missiles look a little different, too.",
      "videoID": "sXG-oI6VChg"
    },
    {
      "id": 5,
      "name": "Yoshi",
      "franchise": "",
      "bio": "",
      "videoID": ""
    },
    {
      "id": 6,
      "name": "Kirby",
      "franchise": "",
      "bio": "",
      "videoID": ""
    },
    {
      "id": 7,
      "name": "Fox",
      "franchise": "",
      "bio": "",
      "videoID": ""
    },
    {
      "id": 8,
      "name": "Pikachu",
      "franchise": "",
      "bio": "",
      "videoID": ""
    },
    {
      "id": 9,
      "name": "Luigi",
      "franchise": "",
      "bio": "",
      "videoID": ""
    },
    {
      "id": 10,
      "name": "Ness",
      "franchise": "",
      "bio": "",
      "videoID": ""
    },
    {
      "id": 11,
      "name": "Captain Falcon",
      "franchise": "",
      "bio": "",
      "videoID": ""
    },
    {
      "id": 12,
      "name": "Jigglypuff",
      "franchise": "",
      "bio": "",
      "videoID": ""
    },
    {
      "id": 13,
      "name": "Peach",
      "franchise": "",
      "bio": "",
      "videoID": ""
    },
    {
      "id": 13.1,
      "name": "Daisy",
      "franchise": "",
      "bio": "",
      "videoID": ""
    },
    {
      "id": 14,
      "name": "Bowser",
      "franchise": "",
      "bio": "",
      "videoID": ""
    },
    {
      "id": 15,
      "name": "Ice Climbers",
      "franchise": "",
      "bio": "",
      "videoID": ""
    },
    {
      "id": 16,
      "name": "Sheik",
      "franchise": "",
      "bio": "",
      "videoID": ""
    },
    {
      "id": 17,
      "name": "Zelda",
      "franchise": "",
      "bio": "",
      "videoID": ""
    },
    {
      "id": 18,
      "name": "Dr. Mario",
      "franchise": "",
      "bio": "",
      "videoID": ""
    },
    {
      "id": 19,
      "name": "Pichu",
      "franchise": "",
      "bio": "",
      "videoID": ""
    },
    {
      "id": 20,
      "name": "Falco",
      "franchise": "",
      "bio": "",
      "videoID": ""
    },
    {
      "id": 21,
      "name": "Marth",
      "franchise": "",
      "bio": "",
      "videoID": ""
    },
    {
      "id": 21.1,
      "name": "Lucina",
      "franchise": "",
      "bio": "",
      "videoID": ""
    },
    {
      "id": 22,
      "name": "Young Link",
      "franchise": "",
      "bio": "",
      "videoID": ""
    },
    {
      "id": 23,
      "name": "Ganondorf",
      "franchise": "",
      "bio": "",
      "videoID": ""
    },
    {
      "id": 24,
      "name": "Mewtwo",
      "franchise": "",
      "bio": "",
      "videoID": ""
    },
    {
      "id": 25,
      "name": "Roy",
      "franchise": "",
      "bio": "",
      "videoID": ""
    },
    {
      "id": 25.1,
      "name": "Chrom",
      "franchise": "",
      "bio": "",
      "videoID": ""
    },
    {
      "id": 26,
      "name": "Mr. Game & Watch",
      "franchise": "",
      "bio": "",
      "videoID": ""
    },
    {
      "id": 27,
      "name": "Meta Knight",
      "franchise": "",
      "bio": "",
      "videoID": ""
    },
    {
      "id": 28,
      "name": "Pit",
      "franchise": "",
      "bio": "",
      "videoID": ""
    },
    {
      "id": 28.1,
      "name": "Dark Pit",
      "franchise": "",
      "bio": "",
      "videoID": ""
    },
    {
      "id": 29,
      "name": "Zero Suit Samus",
      "franchise": "",
      "bio": "",
      "videoID": ""
    },
    {
      "id": 30,
      "name": "Wario",
      "franchise": "",
      "bio": "",
      "videoID": ""
    },
    {
      "id": 31,
      "name": "Snake",
      "franchise": "",
      "bio": "",
      "videoID": ""
    },
    {
      "id": 32,
      "name": "Ike",
      "franchise": "",
      "bio": "",
      "videoID": ""
    },
    {
      "id": 33,
      "name": "Pokemon Trainer",
      "franchise": "",
      "bio": "",
      "videoID": ""
    },
    {
      "id": 36,
      "name": "Diddy Kong",
      "franchise": "",
      "bio": "",
      "videoID": ""
    },
    {
      "id": 37,
      "name": "Lucas",
      "franchise": "",
      "bio": "",
      "videoID": ""
    },
    {
      "id": 38,
      "name": "Sonic",
      "franchise": "",
      "bio": "",
      "videoID": ""
    },
    {
      "id": 39,
      "name": "King Dedede",
      "franchise": "",
      "bio": "",
      "videoID": ""
    },
    {
      "id": 40,
      "name": "Olimar",
      "franchise": "",
      "bio": "",
      "videoID": ""
    },
    {
      "id": 41,
      "name": "Lucario",
      "franchise": "",
      "bio": "",
      "videoID": ""
    },
    {
      "id": 42,
      "name": "R.O.B.",
      "franchise": "",
      "bio": "",
      "videoID": ""
    },
    {
      "id": 43,
      "name": "Toon Link",
      "franchise": "",
      "bio": "",
      "videoID": ""
    },
    {
      "id": 44,
      "name": "Wolf",
      "franchise": "",
      "bio": "",
      "videoID": ""
    },
    {
      "id": 45,
      "name": "Villager",
      "franchise": "",
      "bio": "",
      "videoID": ""
    },
    {
      "id": 46,
      "name": "Mega Man",
      "franchise": "",
      "bio": "",
      "videoID": ""
    },
    {
      "id": 47,
      "name": "Wii Fit Trainer",
      "franchise": "",
      "bio": "",
      "videoID": ""
    },
    {
      "id": 48,
      "name": "Rosalina & Luma",
      "franchise": "",
      "bio": "",
      "videoID": ""
    },
    {
      "id": 49,
      "name": "Little Mac",
      "franchise": "",
      "bio": "",
      "videoID": ""
    },
    {
      "id": 50,
      "name": "Greninja",
      "franchise": "",
      "bio": "",
      "videoID": ""
    },
    {
      "id": 54,
      "name": "Palutena",
      "franchise": "",
      "bio": "",
      "videoID": ""
    },
    {
      "id": 55,
      "name": "Pac-man",
      "franchise": "",
      "bio": "",
      "videoID": ""
    },
    {
      "id": 56,
      "name": "Robin",
      "franchise": "",
      "bio": "",
      "videoID": ""
    },
    {
      "id": 57,
      "name": "Shulk",
      "franchise": "",
      "bio": "",
      "videoID": ""
    },
    {
      "id": 58,
      "name": "Bowser Jr.",
      "franchise": "",
      "bio": "",
      "videoID": ""
    },
    {
      "id": 59,
      "name": "Duck Hunt",
      "franchise": "",
      "bio": "",
      "videoID": ""
    },
    {
      "id": 60,
      "name": "Ryu",
      "franchise": "",
      "bio": "",
      "videoID": ""
    },
    {
      "id": 60.1,
      "name": "Ken",
      "franchise": "",
      "bio": "",
      "videoID": ""
    },
    {
      "id": 61,
      "name": "Cloud",
      "franchise": "",
      "bio": "",
      "videoID": ""
    },
    {
      "id": 62,
      "name": "Corrin",
      "franchise": "",
      "bio": "",
      "videoID": ""
    },
    {
      "id": 63,
      "name": "Bayonetta",
      "franchise": "",
      "bio": "",
      "videoID": ""
    },
    {
      "id": 64,
      "name": "Inkling",
      "franchise": "",
      "bio": "",
      "videoID": ""
    },
    {
      "id": 65,
      "name": "Ridley",
      "franchise": "",
      "bio": "",
      "videoID": ""
    },
    {
      "id": 66,
      "name": "Simon",
      "franchise": "",
      "bio": "",
      "videoID": ""
    },
    {
      "id": 66.1,
      "name": "Richter",
      "franchise": "",
      "bio": "",
      "videoID": ""
    },
    {
      "id": 67,
      "name": "King K. Rool",
      "franchise": "",
      "bio": "",
      "videoID": ""
    },
    {
      "id": 68,
      "name": "Isabelle",
      "franchise": "",
      "bio": "",
      "videoID": ""
    },
    {
      "id": 69,
      "name": "Incineroar",
      "franchise": "",
      "bio": "",
      "videoID": ""
    },
    {
      "id": 70,
      "name": "Piranha Plant",
      "franchise": "",
      "bio": "",
      "videoID": ""
    },
    {
      "id": 71,
      "name": "Joker",
      "franchise": "",
      "bio": "",
      "videoID": ""
    },
    {
      "id": 72,
      "name": "Hero",
      "franchise": "",
      "bio": "",
      "videoID": ""
    },
    {
      "id": 51,
      "name": "Mii Brawler",
      "franchise": "",
      "bio": "",
      "videoID": ""
    },
    {
      "id": 52,
      "name": "Mii Swordfighter",
      "franchise": "",
      "bio": "",
      "videoID": ""
    },
    {
      "id": 53,
      "name": "Mii Gunner",
      "franchise": "",
      "bio": "",
      "videoID": ""
    }
  ]
}
